knobs/__init__.py
knobs/frontend/build/.DS_Store
knobs/frontend/build/asset-manifest.json
knobs/frontend/build/bootstrap.min.css
knobs/frontend/build/index.html
knobs/frontend/build/images/knob1.png
knobs/frontend/build/images/knob1_in.png
knobs/frontend/build/images/knob2.png
knobs/frontend/build/images/knob2_in.png
knobs/frontend/build/images/knob3.png
knobs/frontend/build/images/knob3_in.png
knobs/frontend/build/static/css/main.f20f96a7.css
knobs/frontend/build/static/css/main.f20f96a7.css.map
knobs/frontend/build/static/js/main.48c6904c.js
knobs/frontend/build/static/js/main.48c6904c.js.LICENSE.txt
knobs/frontend/build/static/js/main.48c6904c.js.map
knobs/frontend/build/static/js/main.aa007344.js
knobs/frontend/build/static/js/main.aa007344.js.LICENSE.txt
knobs/frontend/build/static/js/main.aa007344.js.map
knobs/frontend/build/static/js/main.ac6f1bad.js
knobs/frontend/build/static/js/main.ac6f1bad.js.LICENSE.txt
knobs/frontend/build/static/js/main.ac6f1bad.js.map
streamlit-knobs/__init__.py
streamlit_knobs-0.0.4.dist-info/LICENSE
streamlit_knobs-0.0.4.dist-info/METADATA
streamlit_knobs-0.0.4.dist-info/WHEEL
streamlit_knobs-0.0.4.dist-info/top_level.txt
streamlit_knobs-0.0.4.dist-info/RECORD
